{
  "neurons": [
    {
      "index": 0,
      "output": -0.0011621751,
      "input_connections": [
        [
          1,
          0.0
        ],
        [
          2,
          0.0
        ],
        [
          3,
          0.0
        ],
        [
          4,
          0.0
        ],
        [
          5,
          -0.06997538
        ],
        [
          6,
          0.0
        ],
        [
          7,
          -0.005456614
        ]
      ],
      "bias": 0.0,
      "self_activation": 0.0030261388,
      "retina_weights": []
    },
    {
      "index": 1,
      "output": -0.010173884,
      "input_connections": [
        [
          0,
          0.0
        ],
        [
          2,
          0.0
        ],
        [
          3,
          0.0
        ],
        [
          4,
          0.0
        ],
        [
          5,
          0.0
        ],
        [
          6,
          0.0
        ],
        [
          7,
          0.0
        ]
      ],
      "bias": -0.010174235,
      "self_activation": 0.0,
      "retina_weights": []
    },
    {
      "index": 2,
      "output": 0.036250923,
      "input_connections": [
        [
          0,
          0.0
        ],
        [
          1,
          0.0
        ],
        [
          3,
          0.0
        ],
        [
          4,
          0.0
        ],
        [
          5,
          0.0
        ],
        [
          6,
          -0.020858318
        ],
        [
          7,
          0.0
        ]
      ],
      "bias": 0.034186482,
      "self_activation": 0.057787765,
      "retina_weights": []
    },
    {
      "index": 3,
      "output": 0.011303274,
      "input_connections": [
        [
          0,
          0.0
        ],
        [
          1,
          0.0
        ],
        [
          2,
          0.0
        ],
        [
          4,
          0.0
        ],
        [
          5,
          0.0
        ],
        [
          6,
          0.012948751
        ],
        [
          7,
          0.0
        ]
      ],
      "bias": 0.011294738,
      "self_activation": 0.0,
      "retina_weights": []
    },
    {
      "index": 4,
      "output": 0.019045077,
      "input_connections": [
        [
          0,
          0.0
        ],
        [
          1,
          0.0
        ],
        [
          2,
          0.0
        ],
        [
          3,
          0.0
        ],
        [
          5,
          0.0
        ],
        [
          6,
          -0.009929747
        ],
        [
          7,
          0.0
        ]
      ],
      "bias": 0.018185996,
      "self_activation": 0.045591753,
      "retina_weights": []
    },
    {
      "index": 5,
      "output": 0.014708292,
      "input_connections": [
        [
          0,
          0.0
        ],
        [
          1,
          0.0
        ],
        [
          2,
          0.0
        ],
        [
          3,
          0.0
        ],
        [
          4,
          0.0
        ],
        [
          6,
          0.0
        ],
        [
          7,
          0.0
        ]
      ],
      "bias": 0.014630438,
      "self_activation": 0.0053653833,
      "retina_weights": []
    },
    {
      "index": 6,
      "output": 0.0006964015,
      "input_connections": [
        [
          0,
          0.0
        ],
        [
          1,
          -0.06844993
        ],
        [
          2,
          0.0
        ],
        [
          3,
          0.0
        ],
        [
          4,
          0.0
        ],
        [
          5,
          0.0
        ],
        [
          7,
          0.0
        ]
      ],
      "bias": 0.0,
      "self_activation": 0.0,
      "retina_weights": []
    },
    {
      "index": 7,
      "output": 0.023721747,
      "input_connections": [
        [
          0,
          0.0
        ],
        [
          1,
          0.0
        ],
        [
          2,
          0.0
        ],
        [
          3,
          0.0
        ],
        [
          4,
          0.0
        ],
        [
          5,
          0.0
        ],
        [
          6,
          -0.060515903
        ]
      ],
      "bias": 0.022962058,
      "self_activation": 0.03398927,
      "retina_weights": []
    }
  ],
  "short_term_memory": {
    "snapshots": [
      {
        "outputs": [
          -0.0011100217,
          -0.010173884,
          0.034173172,
          0.011294258,
          0.018183991,
          0.014708677,
          0.0006964015,
          0.023408903
        ],
        "time_step": 1
      },
      {
        "outputs": [
          -0.0011603372,
          -0.010173884,
          0.036131013,
          0.011303274,
          0.019005833,
          0.014708294,
          0.0006964015,
          0.023711123
        ],
        "time_step": 2
      },
      {
        "outputs": [
          -0.0011621116,
          -0.010173884,
          0.036244005,
          0.011303274,
          0.019043287,
          0.014708292,
          0.0006964015,
          0.023721386
        ],
        "time_step": 3
      },
      {
        "outputs": [
          -0.0011621729,
          -0.010173884,
          0.036250524,
          0.011303274,
          0.019044993,
          0.014708292,
          0.0006964015,
          0.023721736
        ],
        "time_step": 4
      },
      {
        "outputs": [
          -0.001162175,
          -0.010173884,
          0.0362509,
          0.011303274,
          0.019045074,
          0.014708292,
          0.0006964015,
          0.023721747
        ],
        "time_step": 5
      },
      {
        "outputs": [
          -0.0011621751,
          -0.010173884,
          0.036250923,
          0.011303274,
          0.019045077,
          0.014708292,
          0.0006964015,
          0.023721747
        ],
        "time_step": 6
      },
      {
        "outputs": [
          -0.0011621751,
          -0.010173884,
          0.036250923,
          0.011303274,
          0.019045077,
          0.014708292,
          0.0006964015,
          0.023721747
        ],
        "time_step": 7
      },
      {
        "outputs": [
          -0.0011621751,
          -0.010173884,
          0.036250923,
          0.011303274,
          0.019045077,
          0.014708292,
          0.0006964015,
          0.023721747
        ],
        "time_step": 8
      },
      {
        "outputs": [
          -0.0011621751,
          -0.010173884,
          0.036250923,
          0.011303274,
          0.019045077,
          0.014708292,
          0.0006964015,
          0.023721747
        ],
        "time_step": 9
      },
      {
        "outputs": [
          -0.0011621751,
          -0.010173884,
          0.036250923,
          0.011303274,
          0.019045077,
          0.014708292,
          0.0006964015,
          0.023721747
        ],
        "time_step": 10
      }
    ]
  },
  "graph": {
    "nodes": [
      [
        0,
        0.0
      ],
      [
        1,
        -0.01
      ],
      [
        2,
        0.03
      ],
      [
        3,
        0.01
      ],
      [
        4,
        0.02
      ],
      [
        5,
        0.01
      ],
      [
        6,
        0.0
      ],
      [
        7,
        0.02
      ]
    ],
    "node_holes": [],
    "edge_property": "directed",
    "edges": [
      [
        2,
        2,
        0.06
      ],
      [
        4,
        4,
        0.05
      ],
      [
        5,
        5,
        0.01
      ],
      [
        7,
        7,
        0.03
      ],
      [
        5,
        0,
        -0.07
      ],
      [
        7,
        0,
        -0.01
      ],
      [
        6,
        2,
        -0.02
      ],
      [
        6,
        3,
        0.01
      ],
      [
        6,
        4,
        -0.01
      ],
      [
        1,
        6,
        -0.07
      ],
      [
        6,
        7,
        -0.06
      ]
    ]
  },
  "statistics": {
    "deleted_neurons": 39,
    "deleted_weights": 51,
    "deleted_biases": 51,
    "deleted_self_activations": 49,
    "mutated_neurons": 39,
    "mutated_weights": 53,
    "mutated_biases": 56,
    "mutated_self_activations": 50,
    "fitness": 0.0,
    "variance": 0.021265712
  },
  "mutation_variance": 0.021265712,
  "mean": 0.0
}
